polyapi/__init__.py
polyapi/__main__.py
polyapi/api.py
polyapi/auth.py
polyapi/cli.py
polyapi/client.py
polyapi/config.py
polyapi/constants.py
polyapi/deployables.py
polyapi/error_handler.py
polyapi/exceptions.py
polyapi/execute.py
polyapi/function_cli.py
polyapi/generate.py
polyapi/parser.py
polyapi/poly_schemas.py
polyapi/poly_tables.py
polyapi/prepare.py
polyapi/py.typed
polyapi/rendered_spec.py
polyapi/schema.py
polyapi/server.py
polyapi/sync.py
polyapi/typedefs.py
polyapi/utils.py
polyapi/variables.py
polyapi/webhook.py
polyapi_python-0.3.11.dist-info/licenses/LICENSE
polyapi_python-0.3.11.dist-info/METADATA
polyapi_python-0.3.11.dist-info/WHEEL
polyapi_python-0.3.11.dist-info/top_level.txt
polyapi_python-0.3.11.dist-info/RECORD
