Metadata-Version: 2.4
Name: polyapi-python
Version: 0.3.11
Summary: The Python Client for PolyAPI, the IPaaS by Developers for Developers
Author-email: Dan Fellin <dan@polyapi.io>
License: MIT License
Project-URL: Homepage, https://github.com/polyapi/polyapi-python
Requires-Python: >=3.10
License-File: LICENSE
Requires-Dist: requests>=2.32.3
Requires-Dist: typing_extensions>=4.12.2
Requires-Dist: jsonschema-gentypes==2.6.0
Requires-Dist: pydantic>=2.8.0
Requires-Dist: stdlib_list>=0.10.0
Requires-Dist: colorama==0.4.4
Requires-Dist: python-socketio[asyncio_client]==5.11.1
Requires-Dist: truststore>=0.8.0
Dynamic: license-file
